{
  "sessionId": "12656630069065788236",
  "type": "verification",
  "context": "# 🧹 Code Health Improvement Task\n\nYou are a code health agent. Your mission is to analyze and fix a code health issue that will improve the maintainability and readability of the codebase.\n\n## Task Details\n\n**File:** `include/umpMessageCreate.h:254`\n**Issue:** Bug in mt5MDSPayload loop condition\n\n**Language:** cpp\n\n**Current Code:**\n```cpp\n        for(uint8_t i=1;i<4;i++){\n            if(offset < dataLength)umpMess[i] += (data[offset++] << 24);\n            if(offset < dataLength)umpMess[i] += (data[offset++] << 16);\n            if(offset < dataLength)umpMess[i] += (data[offset++] << 8);\n            if(offset < dataLength)umpMess[i] += data[offset++];\n        }\n        return umpMess;\n    }\n\n//TODO mtD*\n\ninline std::array<uint32_t, 4> mtFMidiEndpoint(uint8_t filter){\n\n```\n\n**Rationale:** Clear bounds check missing. The code checks `if(offset < dataLength)` for the first 3 additions in the loop, but omits it for the 4th, which could lead to an out-of-bounds read on the `data` pointer.\n\n## Your Process\n\n### 1. 🔍 UNDERSTAND - Analyze the Code Health Issue\n* Review the surrounding code and understand its purpose\n* Identify the specific code health problem (duplication, complexity, naming, dead code, deprecated usage, etc.)\n* Consider how this issue affects maintainability and readability\n\n### 2. ⚖️ ASSESS - Evaluate the Risk\nBefore making changes, assess the impact:\n* What other code depends on or references this code?\n* Are there similar patterns elsewhere that should be fixed consistently?\n* What is the risk of inadvertently breaking functionality?\n\n### 3. 📋 PLAN - Design the Improvement\nBased on your assessment, plan your approach:\n* What is the ideal state of this code?\n* Are there existing patterns in the codebase to follow?\n* Will this change affect other parts of the codebase?\n\n### 4. 🔧 IMPLEMENT - Refactor with Care\n* Write clean, readable code that addresses the issue\n* Follow existing codebase patterns and conventions\n* Preserve all existing functionality\n* Ensure the fix doesn't introduce new issues\n* Update or write additional tests if the refactoring warrants coverage\n* Add or update documentation if needed\n\n### 5. ✅ VERIFY - Validate the Improvement\n- Run format and lint checks\n- Run the full test suite\n- Verify the code health issue is resolved\n- Ensure no functionality is broken\n\n### 6. 📝 DOCUMENT - Explain the Improvement\nCreate a PR with:\n- Title: \"🧹 [code health improvement description]\"\n- Description with:\n  * 🎯 **What:** The code health issue addressed\n  * 💡 **Why:** How this improves maintainability\n  * ✅ **Verification:** How you confirmed the change is safe\n  * ✨ **Result:** The improvement achieved\n\nRemember: Code health improvements should make the codebase better without changing behavior. When in doubt, preserve functionality over cleanliness.",
  "diff": "{",
  "status": "pending"
}
